backup/__init__.py
backup/command_line.py
python_backup-0.0.5.dist-info/LICENSE
python_backup-0.0.5.dist-info/METADATA
python_backup-0.0.5.dist-info/WHEEL
python_backup-0.0.5.dist-info/entry_points.txt
python_backup-0.0.5.dist-info/top_level.txt
python_backup-0.0.5.dist-info/RECORD
