Metadata-Version: 2.1
Name: python-backup
Version: 0.0.5
Summary: Configuration file based file backup
Home-page: https://eeems.codes/Eeems/python-backup
Author: Nathaniel van Diepen
Author-email: python-backup@eeems.email
License: UNKNOWN
Platform: UNKNOWN
Classifier: Programming Language :: Python :: 3
Classifier: Programming Language :: Python :: 3 :: Only
Classifier: License :: OSI Approved :: MIT License
Classifier: Operating System :: OS Independent
Classifier: Development Status :: 4 - Beta
Classifier: Environment :: Console
Classifier: Intended Audience :: Information Technology
Classifier: Intended Audience :: End Users/Desktop
Classifier: Natural Language :: English
Classifier: Topic :: System :: Archiving :: Backup
Requires-Python: >=3.6.9
Requires-Dist: blessings (==1.7)
Requires-Dist: intercessions (==1.1.6)
Requires-Dist: PyYAML (==5.3.1)
Requires-Dist: psutil (==5.7.0)
